sipcentric/__init__.py
sipcentric/stream/__init__.py
sipcentric-0.0.0.dist-info/LICENSE
sipcentric-0.0.0.dist-info/METADATA
sipcentric-0.0.0.dist-info/WHEEL
sipcentric-0.0.0.dist-info/top_level.txt
sipcentric-0.0.0.dist-info/RECORD
