Metadata-Version: 2.1
Name: sipcentric
Version: 0.0.0
Summary: Modern Python client library for the Sipsentric (Simwood Partner, formerly Nimvelo) API
Home-page: https://github.com/faelix/sipcentric
Author: Marek Isalski
Author-email: pypi-sipcentric@maz.nu
License: UNKNOWN
Project-URL: Bug Tracker, https://github.com/faelix/sipcentric/issues
Keywords: sipcentric,simwood,nimvelo,voip,pbx,sms,sip
Platform: UNKNOWN
Classifier: Programming Language :: Python :: 3
Classifier: License :: OSI Approved :: MIT License
Classifier: Operating System :: OS Independent
Requires-Python: >=3.6
License-File: LICENSE
Requires-Dist: requests
Requires-Dist: simplejson
